Metadata-Version: 2.1
Name: fastCodePrompts
Version: 0.1.4
Summary: Pegar códigos python e inserir no contexto de um prompt
Home-page: https://github.com/hqr90/fastCodePrompts
Author: Hilton Queiroz Rebello
Author-email: rebello.hiltonqueiroz@gmail.com
License: MIT
Classifier: Programming Language :: Python :: 3
Classifier: License :: OSI Approved :: MIT License
Classifier: Operating System :: OS Independent
Requires-Python: >=3.8
License-File: LICENSE
Requires-Dist: pyperclip
Requires-Dist: argparse
Requires-Dist: PyQt5
